squirrel_datasets_core/__init__.py
squirrel_datasets_core/datasets/AutoML/README.rst
squirrel_datasets_core/datasets/AutoML/__init__.py
squirrel_datasets_core/datasets/AutoML/driver.py
squirrel_datasets_core/datasets/__init__.py
squirrel_datasets_core/datasets/adult_dataset/README.rst
squirrel_datasets_core/datasets/adult_dataset/__init__.py
squirrel_datasets_core/datasets/adult_dataset/driver.py
squirrel_datasets_core/datasets/allenai_c4/README.rst
squirrel_datasets_core/datasets/allenai_c4/__init__.py
squirrel_datasets_core/datasets/allenai_c4/allenai_c4_multilingual.py
squirrel_datasets_core/datasets/allenai_c4/constants.py
squirrel_datasets_core/datasets/bdd100k/README.rst
squirrel_datasets_core/datasets/bdd100k/__init__.py
squirrel_datasets_core/datasets/bdd100k/driver.py
squirrel_datasets_core/datasets/california_housing/README.rst
squirrel_datasets_core/datasets/california_housing/__init__.py
squirrel_datasets_core/datasets/california_housing/driver.py
squirrel_datasets_core/datasets/camvid/README.rst
squirrel_datasets_core/datasets/camvid/__init__.py
squirrel_datasets_core/datasets/camvid/driver.py
squirrel_datasets_core/datasets/cc100/README.rst
squirrel_datasets_core/datasets/cc100/__init__.py
squirrel_datasets_core/datasets/cc100/cc100.py
squirrel_datasets_core/datasets/cc100/constants.py
squirrel_datasets_core/datasets/conceptual_captions/README.rst
squirrel_datasets_core/datasets/conceptual_captions/__init__.py
squirrel_datasets_core/datasets/conceptual_captions/driver.py
squirrel_datasets_core/datasets/ds_bowl_2018/README.rst
squirrel_datasets_core/datasets/ds_bowl_2018/__init__.py
squirrel_datasets_core/datasets/ds_bowl_2018/driver.py
squirrel_datasets_core/datasets/fem_simulations/README.rst
squirrel_datasets_core/datasets/fem_simulations/__init__.py
squirrel_datasets_core/datasets/hugging_face/__init__.py
squirrel_datasets_core/datasets/imagenet/README.rst
squirrel_datasets_core/datasets/imagenet/__init__.py
squirrel_datasets_core-0.3.1.dist-info/LICENSE
squirrel_datasets_core-0.3.1.dist-info/METADATA
squirrel_datasets_core-0.3.1.dist-info/WHEEL
squirrel_datasets_core-0.3.1.dist-info/entry_points.txt
squirrel_datasets_core-0.3.1.dist-info/RECORD
