Metadata-Version: 2.1
Name: squirrel-datasets-core
Version: 0.3.1
Summary: Squirrel public datasets collection
Home-page: https://merantix-momentum.com/technology/squirrel/
License: Apache 2.0
Author: Merantix Momentum
Requires-Python: >=3.8,<4.0
Classifier: Development Status :: 5 - Production/Stable
Classifier: License :: OSI Approved :: Apache Software License
Classifier: License :: Other/Proprietary License
Classifier: Programming Language :: Python :: 3
Classifier: Programming Language :: Python :: 3.8
Classifier: Programming Language :: Python :: 3.9
Classifier: Programming Language :: Python :: 3.10
Classifier: Programming Language :: Python :: 3.11
Classifier: Programming Language :: Python :: 3.9
Classifier: Typing :: Typed
Provides-Extra: all
Provides-Extra: deeplake
Provides-Extra: hub
Provides-Extra: huggingface
Provides-Extra: preprocessing
Provides-Extra: torchvision
Requires-Dist: datasets (>=2.9.0,<3.0.0) ; extra == "huggingface" or extra == "all"
Requires-Dist: deeplake (>=3.2.7,<4.0.0) ; extra == "deeplake" or extra == "all"
Requires-Dist: docutils (>=0.17.1,<0.18.0)
Requires-Dist: fire (>=0.4.0,<0.5.0)
Requires-Dist: hub (>=3.0.1,<4.0.0) ; extra == "hub" or extra == "all"
Requires-Dist: pillow (>=9.4.0,<10.0.0)
Requires-Dist: pyspark (>=3.3.2,<4.0.0) ; extra == "preprocessing" or extra == "all"
Requires-Dist: scipy (>=1.9.3,<2.0.0)
Requires-Dist: squirrel-core[gcp,zarr] (>=0.19.0,<0.20.0)
Requires-Dist: torchvision (>=0.14.1,<0.15.0) ; extra == "torchvision" or extra == "all"
Project-URL: Documentation, https://squirrel-datasets-core.readthedocs.io/en/latest/
Project-URL: Repository, https://github.com/merantix-momentum/squirrel-datasets-core
